{
  "$schema": "https://raw.githubusercontent.com/googleapis/release-please/main/schemas/config.json",
  "packages": {
    ".": {
      "changelog-path": "CHANGELOG.md",
      "release-type": "node",
      "bump-minor-pre-major": false,
      "bump-patch-for-minor-pre-major": false,
      "draft": false,
      "prerelease": false
    }
  },
  "include-v-in-tag": false,
  "include-component-in-tag": false,
  "initial-version": "1.0.1",
  "bootstrap": true,
  "pull-request-header": "Pedro-Bot Release\n\nThis pull request contains all merged changes since the last release. See the changelog below for details.",
  "pull-request-footer": "This PR is automatically generated by [release-please](https://github.com/googleapis/release-please)."
}
